socialreaper/__init__.py
socialreaper/apis.py
socialreaper/exceptions.py
socialreaper/generators.py
socialreaper/tools.py
socialreaper-0.3.0.dist-info/DESCRIPTION.rst
socialreaper-0.3.0.dist-info/METADATA
socialreaper-0.3.0.dist-info/RECORD
socialreaper-0.3.0.dist-info/WHEEL
socialreaper-0.3.0.dist-info/metadata.json
socialreaper-0.3.0.dist-info/top_level.txt
