Metadata-Version: 2.0
Name: socialreaper
Version: 0.3.0
Summary: Social media scraping for Facebook, Twitter, Reddit and Youtube
Home-page: https://github.com/ScriptSmith/socialreaper
Author: Adam Smith
Author-email: adamdevsmith@gmail.com
License: MIT
Keywords: social media socialmedia facebook twitter reddit youtube scrape
Platform: UNKNOWN
Requires-Dist: oauthlib (>=2.0.1)
Requires-Dist: requests (>=2.11.1)
Requires-Dist: requests-oauthlib (>=0.7.0)
